{"box_data": [{"position": {"minX": 166.875, "minY": 180.75, "maxX": 199.875, "maxY": 212.75}, "class_id": 14, "box_caption": "4h 0.942", "scores": {"class_score": 0.94189453125}, "domain": "pixel"}, {"position": {"minX": 341.5, "minY": 195.25, "maxX": 373.5, "maxY": 226.75}, "class_id": 14, "box_caption": "4h 0.932", "scores": {"class_score": 0.931640625}, "domain": "pixel"}, {"position": {"minX": 169.5, "minY": 17.9375, "maxX": 209.0, "maxY": 49.875}, "class_id": 19, "box_caption": "5s 0.928", "scores": {"class_score": 0.92822265625}, "domain": "pixel"}, {"position": {"minX": 111.6875, "minY": 189.125, "maxX": 150.0, "maxY": 220.625}, "class_id": 19, "box_caption": "5s 0.920", "scores": {"class_score": 0.92041015625}, "domain": "pixel"}, {"position": {"minX": 111.75, "minY": 189.125, "maxX": 150.0, "maxY": 220.625}, "class_id": 7, "box_caption": "2s 0.012", "scores": {"class_score": 0.01215362548828125}, "domain": "pixel"}, {"position": {"minX": 167.0, "minY": 180.75, "maxX": 199.5, "maxY": 213.25}, "class_id": 6, "box_caption": "2h 0.011", "scores": {"class_score": 0.0114288330078125}, "domain": "pixel"}, {"position": {"minX": 169.5, "minY": 17.90625, "maxX": 208.75, "maxY": 49.78125}, "class_id": 7, "box_caption": "2s 0.011", "scores": {"class_score": 0.0113983154296875}, "domain": "pixel"}, {"position": {"minX": 341.75, "minY": 195.375, "maxX": 372.75, "maxY": 227.375}, "class_id": 13, "box_caption": "4d 0.011", "scores": {"class_score": 0.01126861572265625}, "domain": "pixel"}, {"position": {"minX": 111.125, "minY": 188.125, "maxX": 149.875, "maxY": 219.375}, "class_id": 23, "box_caption": "6s 0.011", "scores": {"class_score": 0.01117706298828125}, "domain": "pixel"}, {"position": {"minX": 111.75, "minY": 189.125, "maxX": 150.0, "maxY": 220.625}, "class_id": 16, "box_caption": "5c 0.011", "scores": {"class_score": 0.0106964111328125}, "domain": "pixel"}, {"position": {"minX": 167.375, "minY": 180.75, "maxX": 199.375, "maxY": 212.5}, "class_id": 13, "box_caption": "4d 0.011", "scores": {"class_score": 0.01056671142578125}, "domain": "pixel"}, {"position": {"minX": 167.0, "minY": 180.75, "maxX": 199.5, "maxY": 213.25}, "class_id": 18, "box_caption": "5h 0.010", "scores": {"class_score": 0.00983428955078125}, "domain": "pixel"}, {"position": {"minX": 169.5, "minY": 17.90625, "maxX": 208.75, "maxY": 49.78125}, "class_id": 16, "box_caption": "5c 0.010", "scores": {"class_score": 0.00957489013671875}, "domain": "pixel"}, {"position": {"minX": 169.625, "minY": 18.078125, "maxX": 208.875, "maxY": 50.125}, "class_id": 17, "box_caption": "5d 0.009", "scores": {"class_score": 0.00925445556640625}, "domain": "pixel"}, {"position": {"minX": 111.6875, "minY": 189.125, "maxX": 150.125, "maxY": 220.625}, "class_id": 17, "box_caption": "5d 0.009", "scores": {"class_score": 0.009002685546875}, "domain": "pixel"}, {"position": {"minX": 169.5, "minY": 17.78125, "maxX": 208.75, "maxY": 49.96875}, "class_id": 23, "box_caption": "6s 0.009", "scores": {"class_score": 0.00899505615234375}, "domain": "pixel"}, {"position": {"minX": 167.25, "minY": 180.875, "maxX": 200.0, "maxY": 212.625}, "class_id": 12, "box_caption": "4c 0.009", "scores": {"class_score": 0.00885009765625}, "domain": "pixel"}, {"position": {"minX": 342.0, "minY": 195.25, "maxX": 373.0, "maxY": 227.25}, "class_id": 12, "box_caption": "4c 0.009", "scores": {"class_score": 0.00860595703125}, "domain": "pixel"}, {"position": {"minX": 342.0, "minY": 195.25, "maxX": 373.0, "maxY": 227.25}, "class_id": 22, "box_caption": "6h 0.008", "scores": {"class_score": 0.00821685791015625}, "domain": "pixel"}, {"position": {"minX": 169.5, "minY": 17.90625, "maxX": 208.75, "maxY": 49.78125}, "class_id": 5, "box_caption": "2d 0.008", "scores": {"class_score": 0.00789642333984375}, "domain": "pixel"}, {"position": {"minX": 111.6875, "minY": 189.125, "maxX": 150.125, "maxY": 220.625}, "class_id": 5, "box_caption": "2d 0.008", "scores": {"class_score": 0.0078277587890625}, "domain": "pixel"}, {"position": {"minX": 111.125, "minY": 188.125, "maxX": 149.875, "maxY": 219.375}, "class_id": 15, "box_caption": "4s 0.008", "scores": {"class_score": 0.007801055908203125}, "domain": "pixel"}, {"position": {"minX": 342.0, "minY": 195.25, "maxX": 373.0, "maxY": 227.25}, "class_id": 50, "box_caption": "Qh 0.008", "scores": {"class_score": 0.007724761962890625}, "domain": "pixel"}, {"position": {"minX": 342.0, "minY": 195.25, "maxX": 373.0, "maxY": 227.25}, "class_id": 26, "box_caption": "7h 0.008", "scores": {"class_score": 0.007572174072265625}, "domain": "pixel"}, {"position": {"minX": 167.25, "minY": 180.875, "maxX": 200.0, "maxY": 212.625}, "class_id": 50, "box_caption": "Qh 0.007", "scores": {"class_score": 0.007434844970703125}, "domain": "pixel"}, {"position": {"minX": 167.5, "minY": 180.5, "maxX": 200.5, "maxY": 213.0}, "class_id": 35, "box_caption": "9s 0.007", "scores": {"class_score": 0.007411956787109375}, "domain": "pixel"}, {"position": {"minX": 111.125, "minY": 188.125, "maxX": 149.875, "maxY": 219.375}, "class_id": 45, "box_caption": "Kd 0.007", "scores": {"class_score": 0.007305145263671875}, "domain": "pixel"}, {"position": {"minX": 167.25, "minY": 180.875, "maxX": 200.0, "maxY": 212.625}, "class_id": 22, "box_caption": "6h 0.007", "scores": {"class_score": 0.007183074951171875}, "domain": "pixel"}, {"position": {"minX": 342.0, "minY": 195.25, "maxX": 373.0, "maxY": 227.25}, "class_id": 0, "box_caption": "10c 0.007", "scores": {"class_score": 0.00714874267578125}, "domain": "pixel"}, {"position": {"minX": 167.25, "minY": 180.875, "maxX": 200.0, "maxY": 212.625}, "class_id": 26, "box_caption": "7h 0.007", "scores": {"class_score": 0.00696563720703125}, "domain": "pixel"}, {"position": {"minX": 167.25, "minY": 180.875, "maxX": 200.0, "maxY": 212.625}, "class_id": 0, "box_caption": "10c 0.006", "scores": {"class_score": 0.00649261474609375}, "domain": "pixel"}, {"position": {"minX": 341.75, "minY": 195.375, "maxX": 373.25, "maxY": 227.375}, "class_id": 6, "box_caption": "2h 0.006", "scores": {"class_score": 0.00643157958984375}, "domain": "pixel"}, {"position": {"minX": 342.0, "minY": 195.0, "maxX": 373.0, "maxY": 227.5}, "class_id": 35, "box_caption": "9s 0.006", "scores": {"class_score": 0.006023406982421875}, "domain": "pixel"}, {"position": {"minX": 342.0, "minY": 195.25, "maxX": 373.0, "maxY": 227.25}, "class_id": 18, "box_caption": "5h 0.006", "scores": {"class_score": 0.0059356689453125}, "domain": "pixel"}, {"position": {"minX": 169.5, "minY": 17.90625, "maxX": 208.5, "maxY": 50.15625}, "class_id": 11, "box_caption": "3s 0.006", "scores": {"class_score": 0.00569915771484375}, "domain": "pixel"}, {"position": {"minX": 167.0, "minY": 181.0, "maxX": 200.0, "maxY": 212.5}, "class_id": 46, "box_caption": "Kh 0.006", "scores": {"class_score": 0.005645751953125}, "domain": "pixel"}, {"position": {"minX": 169.5, "minY": 17.984375, "maxX": 209.0, "maxY": 50.0}, "class_id": 45, "box_caption": "Kd 0.006", "scores": {"class_score": 0.00562286376953125}, "domain": "pixel"}, {"position": {"minX": 111.6875, "minY": 189.125, "maxX": 150.125, "maxY": 220.625}, "class_id": 11, "box_caption": "3s 0.005", "scores": {"class_score": 0.005481719970703125}, "domain": "pixel"}, {"position": {"minX": 169.5, "minY": 17.984375, "maxX": 209.0, "maxY": 50.0}, "class_id": 15, "box_caption": "4s 0.005", "scores": {"class_score": 0.005428314208984375}, "domain": "pixel"}, {"position": {"minX": 341.5, "minY": 195.25, "maxX": 373.5, "maxY": 226.75}, "class_id": 21, "box_caption": "6d 0.005", "scores": {"class_score": 0.00510406494140625}, "domain": "pixel"}, {"position": {"minX": 342.0, "minY": 195.0, "maxX": 373.0, "maxY": 227.5}, "class_id": 46, "box_caption": "Kh 0.005", "scores": {"class_score": 0.004940032958984375}, "domain": "pixel"}, {"position": {"minX": 111.5, "minY": 188.75, "maxX": 150.0, "maxY": 220.5}, "class_id": 0, "box_caption": "10c 0.005", "scores": {"class_score": 0.0045928955078125}, "domain": "pixel"}, {"position": {"minX": 166.875, "minY": 180.75, "maxX": 199.875, "maxY": 212.75}, "class_id": 21, "box_caption": "6d 0.004", "scores": {"class_score": 0.004329681396484375}, "domain": "pixel"}, {"position": {"minX": 167.0, "minY": 180.75, "maxX": 199.5, "maxY": 213.25}, "class_id": 37, "box_caption": "Ad 0.004", "scores": {"class_score": 0.004276275634765625}, "domain": "pixel"}, {"position": {"minX": 342.0, "minY": 195.0, "maxX": 373.0, "maxY": 227.5}, "class_id": 37, "box_caption": "Ad 0.004", "scores": {"class_score": 0.004230499267578125}, "domain": "pixel"}, {"position": {"minX": 342.25, "minY": 195.375, "maxX": 372.75, "maxY": 227.125}, "class_id": 38, "box_caption": "Ah 0.004", "scores": {"class_score": 0.004116058349609375}, "domain": "pixel"}, {"position": {"minX": 167.0, "minY": 180.75, "maxX": 199.5, "maxY": 213.25}, "class_id": 24, "box_caption": "7c 0.004", "scores": {"class_score": 0.00409698486328125}, "domain": "pixel"}, {"position": {"minX": 170.25, "minY": 17.78125, "maxX": 208.0, "maxY": 49.46875}, "class_id": 31, "box_caption": "8s 0.004", "scores": {"class_score": 0.004070281982421875}, "domain": "pixel"}, {"position": {"minX": 111.5, "minY": 188.75, "maxX": 150.0, "maxY": 220.5}, "class_id": 26, "box_caption": "7h 0.004", "scores": {"class_score": 0.004058837890625}, "domain": "pixel"}, {"position": {"minX": 167.125, "minY": 181.0, "maxX": 199.875, "maxY": 212.5}, "class_id": 38, "box_caption": "Ah 0.004", "scores": {"class_score": 0.003993988037109375}, "domain": "pixel"}, {"position": {"minX": 167.25, "minY": 180.875, "maxX": 200.0, "maxY": 212.625}, "class_id": 41, "box_caption": "Jd 0.004", "scores": {"class_score": 0.0039215087890625}, "domain": "pixel"}, {"position": {"minX": 170.25, "minY": 17.78125, "maxX": 208.0, "maxY": 49.46875}, "class_id": 28, "box_caption": "8c 0.004", "scores": {"class_score": 0.0039005279541015625}, "domain": "pixel"}, {"position": {"minX": 167.5, "minY": 180.5, "maxX": 200.5, "maxY": 213.0}, "class_id": 2, "box_caption": "10h 0.004", "scores": {"class_score": 0.0037441253662109375}, "domain": "pixel"}, {"position": {"minX": 341.75, "minY": 195.375, "maxX": 373.25, "maxY": 227.125}, "class_id": 1, "box_caption": "10d 0.004", "scores": {"class_score": 0.0037078857421875}, "domain": "pixel"}, {"position": {"minX": 169.25, "minY": 18.09375, "maxX": 208.75, "maxY": 50.09375}, "class_id": 0, "box_caption": "10c 0.004", "scores": {"class_score": 0.0036983489990234375}, "domain": "pixel"}, {"position": {"minX": 166.875, "minY": 180.75, "maxX": 199.875, "maxY": 212.75}, "class_id": 1, "box_caption": "10d 0.004", "scores": {"class_score": 0.003635406494140625}, "domain": "pixel"}, {"position": {"minX": 342.0, "minY": 195.5, "maxX": 373.0, "maxY": 227.25}, "class_id": 2, "box_caption": "10h 0.004", "scores": {"class_score": 0.0035610198974609375}, "domain": "pixel"}, {"position": {"minX": 341.75, "minY": 195.375, "maxX": 372.75, "maxY": 227.375}, "class_id": 41, "box_caption": "Jd 0.004", "scores": {"class_score": 0.0035114288330078125}, "domain": "pixel"}, {"position": {"minX": 169.5, "minY": 17.984375, "maxX": 209.0, "maxY": 50.0}, "class_id": 26, "box_caption": "7h 0.003", "scores": {"class_score": 0.0034465789794921875}, "domain": "pixel"}, {"position": {"minX": 112.25, "minY": 189.125, "maxX": 149.25, "maxY": 220.375}, "class_id": 31, "box_caption": "8s 0.003", "scores": {"class_score": 0.003429412841796875}, "domain": "pixel"}, {"position": {"minX": 111.125, "minY": 188.125, "maxX": 149.875, "maxY": 219.375}, "class_id": 33, "box_caption": "9d 0.003", "scores": {"class_score": 0.0033721923828125}, "domain": "pixel"}, {"position": {"minX": 169.5, "minY": 17.90625, "maxX": 208.75, "maxY": 49.78125}, "class_id": 36, "box_caption": "Ac 0.003", "scores": {"class_score": 0.003360748291015625}, "domain": "pixel"}, {"position": {"minX": 342.0, "minY": 195.0, "maxX": 373.0, "maxY": 227.5}, "class_id": 24, "box_caption": "7c 0.003", "scores": {"class_score": 0.0033111572265625}, "domain": "pixel"}, {"position": {"minX": 169.5, "minY": 17.984375, "maxX": 209.0, "maxY": 50.0}, "class_id": 33, "box_caption": "9d 0.003", "scores": {"class_score": 0.003200531005859375}, "domain": "pixel"}, {"position": {"minX": 112.25, "minY": 189.125, "maxX": 149.25, "maxY": 220.375}, "class_id": 28, "box_caption": "8c 0.003", "scores": {"class_score": 0.00296783447265625}, "domain": "pixel"}, {"position": {"minX": 111.75, "minY": 189.125, "maxX": 150.0, "maxY": 220.625}, "class_id": 36, "box_caption": "Ac 0.003", "scores": {"class_score": 0.002964019775390625}, "domain": "pixel"}, {"position": {"minX": 170.25, "minY": 17.78125, "maxX": 208.0, "maxY": 49.46875}, "class_id": 20, "box_caption": "6c 0.003", "scores": {"class_score": 0.0029354095458984375}, "domain": "pixel"}, {"position": {"minX": 167.0, "minY": 180.75, "maxX": 199.5, "maxY": 213.25}, "class_id": 10, "box_caption": "3h 0.003", "scores": {"class_score": 0.002933502197265625}, "domain": "pixel"}, {"position": {"minX": 342.0, "minY": 195.0, "maxX": 373.0, "maxY": 227.5}, "class_id": 44, "box_caption": "Kc 0.003", "scores": {"class_score": 0.0028896331787109375}, "domain": "pixel"}, {"position": {"minX": 111.5, "minY": 188.75, "maxX": 150.0, "maxY": 220.5}, "class_id": 4, "box_caption": "2c 0.003", "scores": {"class_score": 0.0027828216552734375}, "domain": "pixel"}, {"position": {"minX": 169.5, "minY": 17.90625, "maxX": 208.75, "maxY": 49.78125}, "class_id": 24, "box_caption": "7c 0.003", "scores": {"class_score": 0.0027332305908203125}, "domain": "pixel"}, {"position": {"minX": 111.5, "minY": 188.75, "maxX": 150.0, "maxY": 220.5}, "class_id": 12, "box_caption": "4c 0.003", "scores": {"class_score": 0.002696990966796875}, "domain": "pixel"}, {"position": {"minX": 111.75, "minY": 189.125, "maxX": 150.0, "maxY": 220.625}, "class_id": 24, "box_caption": "7c 0.003", "scores": {"class_score": 0.002666473388671875}, "domain": "pixel"}, {"position": {"minX": 169.625, "minY": 18.078125, "maxX": 208.875, "maxY": 50.125}, "class_id": 21, "box_caption": "6d 0.003", "scores": {"class_score": 0.002651214599609375}, "domain": "pixel"}, {"position": {"minX": 342.25, "minY": 195.375, "maxX": 372.75, "maxY": 227.125}, "class_id": 33, "box_caption": "9d 0.003", "scores": {"class_score": 0.002628326416015625}, "domain": "pixel"}, {"position": {"minX": 112.25, "minY": 189.375, "maxX": 149.5, "maxY": 220.375}, "class_id": 20, "box_caption": "6c 0.003", "scores": {"class_score": 0.0025959014892578125}, "domain": "pixel"}, {"position": {"minX": 170.25, "minY": 17.78125, "maxX": 208.0, "maxY": 49.46875}, "class_id": 51, "box_caption": "Qs 0.003", "scores": {"class_score": 0.0025310516357421875}, "domain": "pixel"}, {"position": {"minX": 167.25, "minY": 180.875, "maxX": 200.0, "maxY": 212.625}, "class_id": 49, "box_caption": "Qd 0.002", "scores": {"class_score": 0.0024356842041015625}, "domain": "pixel"}, {"position": {"minX": 342.0, "minY": 195.25, "maxX": 373.0, "maxY": 227.25}, "class_id": 49, "box_caption": "Qd 0.002", "scores": {"class_score": 0.0024356842041015625}, "domain": "pixel"}, {"position": {"minX": 167.0, "minY": 180.75, "maxX": 199.5, "maxY": 213.25}, "class_id": 44, "box_caption": "Kc 0.002", "scores": {"class_score": 0.002414703369140625}, "domain": "pixel"}, {"position": {"minX": 166.875, "minY": 180.75, "maxX": 199.875, "maxY": 212.75}, "class_id": 33, "box_caption": "9d 0.002", "scores": {"class_score": 0.0024051666259765625}, "domain": "pixel"}, {"position": {"minX": 111.75, "minY": 189.125, "maxX": 150.0, "maxY": 220.625}, "class_id": 21, "box_caption": "6d 0.002", "scores": {"class_score": 0.0023365020751953125}, "domain": "pixel"}, {"position": {"minX": 169.25, "minY": 18.09375, "maxX": 208.75, "maxY": 50.09375}, "class_id": 4, "box_caption": "2c 0.002", "scores": {"class_score": 0.0023345947265625}, "domain": "pixel"}, {"position": {"minX": 167.0, "minY": 180.75, "maxX": 199.5, "maxY": 213.25}, "class_id": 4, "box_caption": "2c 0.002", "scores": {"class_score": 0.002330780029296875}, "domain": "pixel"}, {"position": {"minX": 169.625, "minY": 18.078125, "maxX": 208.875, "maxY": 50.125}, "class_id": 12, "box_caption": "4c 0.002", "scores": {"class_score": 0.00225067138671875}, "domain": "pixel"}, {"position": {"minX": 342.0, "minY": 195.25, "maxX": 373.0, "maxY": 227.25}, "class_id": 17, "box_caption": "5d 0.002", "scores": {"class_score": 0.0022430419921875}, "domain": "pixel"}, {"position": {"minX": 169.5, "minY": 17.984375, "maxX": 209.0, "maxY": 50.0}, "class_id": 13, "box_caption": "4d 0.002", "scores": {"class_score": 0.0022029876708984375}, "domain": "pixel"}, {"position": {"minX": 111.5, "minY": 188.75, "maxX": 150.0, "maxY": 220.5}, "class_id": 13, "box_caption": "4d 0.002", "scores": {"class_score": 0.002193450927734375}, "domain": "pixel"}, {"position": {"minX": 167.25, "minY": 180.875, "maxX": 200.0, "maxY": 212.625}, "class_id": 17, "box_caption": "5d 0.002", "scores": {"class_score": 0.002185821533203125}, "domain": "pixel"}, {"position": {"minX": 111.8125, "minY": 189.125, "maxX": 149.75, "maxY": 220.625}, "class_id": 51, "box_caption": "Qs 0.002", "scores": {"class_score": 0.0021610260009765625}, "domain": "pixel"}, {"position": {"minX": 167.25, "minY": 180.875, "maxX": 200.0, "maxY": 212.625}, "class_id": 23, "box_caption": "6s 0.002", "scores": {"class_score": 0.0021514892578125}, "domain": "pixel"}, {"position": {"minX": 341.75, "minY": 195.375, "maxX": 373.25, "maxY": 227.375}, "class_id": 10, "box_caption": "3h 0.002", "scores": {"class_score": 0.002147674560546875}, "domain": "pixel"}, {"position": {"minX": 342.0, "minY": 195.25, "maxX": 373.0, "maxY": 227.25}, "class_id": 23, "box_caption": "6s 0.002", "scores": {"class_score": 0.0021076202392578125}, "domain": "pixel"}, {"position": {"minX": 342.0, "minY": 195.5, "maxX": 373.0, "maxY": 227.25}, "class_id": 42, "box_caption": "Jh 0.002", "scores": {"class_score": 0.002105712890625}, "domain": "pixel"}, {"position": {"minX": 167.5, "minY": 180.5, "maxX": 200.5, "maxY": 213.0}, "class_id": 42, "box_caption": "Jh 0.002", "scores": {"class_score": 0.0020236968994140625}, "domain": "pixel"}, {"position": {"minX": 111.75, "minY": 189.125, "maxX": 150.0, "maxY": 220.625}, "class_id": 39, "box_caption": "As 0.002", "scores": {"class_score": 0.0020084381103515625}, "domain": "pixel"}, {"position": {"minX": 167.25, "minY": 180.875, "maxX": 200.0, "maxY": 212.625}, "class_id": 8, "box_caption": "3c 0.002", "scores": {"class_score": 0.0019893646240234375}, "domain": "pixel"}, {"position": {"minX": 342.0, "minY": 195.25, "maxX": 373.0, "maxY": 227.25}, "class_id": 8, "box_caption": "3c 0.002", "scores": {"class_score": 0.0019817352294921875}, "domain": "pixel"}, {"position": {"minX": 342.0, "minY": 195.5, "maxX": 373.0, "maxY": 227.25}, "class_id": 4, "box_caption": "2c 0.002", "scores": {"class_score": 0.001880645751953125}, "domain": "pixel"}, {"position": {"minX": 169.5, "minY": 17.984375, "maxX": 209.0, "maxY": 50.0}, "class_id": 30, "box_caption": "8h 0.002", "scores": {"class_score": 0.0018558502197265625}, "domain": "pixel"}, {"position": {"minX": 167.25, "minY": 180.875, "maxX": 200.0, "maxY": 212.625}, "class_id": 11, "box_caption": "3s 0.002", "scores": {"class_score": 0.0018405914306640625}, "domain": "pixel"}, {"position": {"minX": 167.0, "minY": 180.75, "maxX": 199.5, "maxY": 213.25}, "class_id": 19, "box_caption": "5s 0.002", "scores": {"class_score": 0.0018091201782226562}, "domain": "pixel"}, {"position": {"minX": 342.0, "minY": 195.25, "maxX": 373.0, "maxY": 227.25}, "class_id": 11, "box_caption": "3s 0.002", "scores": {"class_score": 0.0017976760864257812}, "domain": "pixel"}, {"position": {"minX": 111.75, "minY": 189.125, "maxX": 150.0, "maxY": 220.625}, "class_id": 34, "box_caption": "9h 0.002", "scores": {"class_score": 0.00179290771484375}, "domain": "pixel"}, {"position": {"minX": 111.5, "minY": 188.75, "maxX": 150.0, "maxY": 220.5}, "class_id": 30, "box_caption": "8h 0.002", "scores": {"class_score": 0.0017633438110351562}, "domain": "pixel"}, {"position": {"minX": 169.5, "minY": 17.90625, "maxX": 208.75, "maxY": 49.78125}, "class_id": 39, "box_caption": "As 0.002", "scores": {"class_score": 0.001705169677734375}, "domain": "pixel"}, {"position": {"minX": 167.25, "minY": 180.875, "maxX": 200.0, "maxY": 212.625}, "class_id": 51, "box_caption": "Qs 0.002", "scores": {"class_score": 0.0016832351684570312}, "domain": "pixel"}, {"position": {"minX": 169.25, "minY": 18.09375, "maxX": 208.75, "maxY": 50.09375}, "class_id": 27, "box_caption": "7s 0.002", "scores": {"class_score": 0.0016641616821289062}, "domain": "pixel"}, {"position": {"minX": 342.0, "minY": 195.25, "maxX": 373.0, "maxY": 227.25}, "class_id": 51, "box_caption": "Qs 0.002", "scores": {"class_score": 0.0016431808471679688}, "domain": "pixel"}, {"position": {"minX": 169.5, "minY": 17.90625, "maxX": 208.75, "maxY": 49.78125}, "class_id": 34, "box_caption": "9h 0.002", "scores": {"class_score": 0.0016336441040039062}, "domain": "pixel"}, {"position": {"minX": 111.625, "minY": 189.0, "maxX": 149.875, "maxY": 220.5}, "class_id": 27, "box_caption": "7s 0.002", "scores": {"class_score": 0.001617431640625}, "domain": "pixel"}, {"position": {"minX": 342.0, "minY": 195.0, "maxX": 373.0, "maxY": 227.5}, "class_id": 3, "box_caption": "10s 0.002", "scores": {"class_score": 0.0016164779663085938}, "domain": "pixel"}, {"position": {"minX": 111.5, "minY": 188.75, "maxX": 150.0, "maxY": 220.5}, "class_id": 14, "box_caption": "4h 0.002", "scores": {"class_score": 0.0016117095947265625}, "domain": "pixel"}, {"position": {"minX": 341.5, "minY": 195.5, "maxX": 373.5, "maxY": 227.25}, "class_id": 34, "box_caption": "9h 0.002", "scores": {"class_score": 0.0015840530395507812}, "domain": "pixel"}, {"position": {"minX": 111.6875, "minY": 189.125, "maxX": 150.125, "maxY": 220.625}, "class_id": 46, "box_caption": "Kh 0.002", "scores": {"class_score": 0.0015592575073242188}, "domain": "pixel"}, {"position": {"minX": 111.75, "minY": 189.125, "maxX": 150.0, "maxY": 220.625}, "class_id": 40, "box_caption": "Jc 0.002", "scores": {"class_score": 0.0015583038330078125}, "domain": "pixel"}, {"position": {"minX": 169.625, "minY": 18.078125, "maxX": 208.875, "maxY": 50.125}, "class_id": 37, "box_caption": "Ad 0.002", "scores": {"class_score": 0.0015239715576171875}, "domain": "pixel"}, {"position": {"minX": 111.625, "minY": 189.0, "maxX": 149.875, "maxY": 220.5}, "class_id": 50, "box_caption": "Qh 0.002", "scores": {"class_score": 0.0015201568603515625}, "domain": "pixel"}, {"position": {"minX": 169.5, "minY": 17.90625, "maxX": 208.75, "maxY": 49.78125}, "class_id": 50, "box_caption": "Qh 0.001", "scores": {"class_score": 0.0014591217041015625}, "domain": "pixel"}, {"position": {"minX": 167.125, "minY": 181.0, "maxX": 199.875, "maxY": 212.5}, "class_id": 34, "box_caption": "9h 0.001", "scores": {"class_score": 0.0014562606811523438}, "domain": "pixel"}, {"position": {"minX": 342.0, "minY": 195.25, "maxX": 373.0, "maxY": 227.25}, "class_id": 16, "box_caption": "5c 0.001", "scores": {"class_score": 0.0014562606811523438}, "domain": "pixel"}, {"position": {"minX": 111.625, "minY": 189.0, "maxX": 149.875, "maxY": 220.5}, "class_id": 2, "box_caption": "10h 0.001", "scores": {"class_score": 0.0014505386352539062}, "domain": "pixel"}, {"position": {"minX": 169.5, "minY": 17.90625, "maxX": 208.75, "maxY": 49.78125}, "class_id": 40, "box_caption": "Jc 0.001", "scores": {"class_score": 0.0014486312866210938}, "domain": "pixel"}, {"position": {"minX": 167.25, "minY": 180.875, "maxX": 200.0, "maxY": 212.625}, "class_id": 32, "box_caption": "9c 0.001", "scores": {"class_score": 0.001445770263671875}, "domain": "pixel"}, {"position": {"minX": 169.5, "minY": 17.90625, "maxX": 208.75, "maxY": 49.78125}, "class_id": 32, "box_caption": "9c 0.001", "scores": {"class_score": 0.0014371871948242188}, "domain": "pixel"}, {"position": {"minX": 167.25, "minY": 180.875, "maxX": 200.0, "maxY": 212.625}, "class_id": 3, "box_caption": "10s 0.001", "scores": {"class_score": 0.001434326171875}, "domain": "pixel"}, {"position": {"minX": 341.75, "minY": 195.375, "maxX": 373.25, "maxY": 227.375}, "class_id": 19, "box_caption": "5s 0.001", "scores": {"class_score": 0.00142669677734375}, "domain": "pixel"}, {"position": {"minX": 111.75, "minY": 189.125, "maxX": 150.0, "maxY": 220.625}, "class_id": 43, "box_caption": "Js 0.001", "scores": {"class_score": 0.0014238357543945312}, "domain": "pixel"}, {"position": {"minX": 111.75, "minY": 189.125, "maxX": 150.0, "maxY": 220.625}, "class_id": 32, "box_caption": "9c 0.001", "scores": {"class_score": 0.001407623291015625}, "domain": "pixel"}, {"position": {"minX": 167.25, "minY": 180.875, "maxX": 200.0, "maxY": 212.625}, "class_id": 16, "box_caption": "5c 0.001", "scores": {"class_score": 0.0014019012451171875}, "domain": "pixel"}, {"position": {"minX": 169.5, "minY": 17.78125, "maxX": 208.75, "maxY": 49.96875}, "class_id": 46, "box_caption": "Kh 0.001", "scores": {"class_score": 0.0013971328735351562}, "domain": "pixel"}, {"position": {"minX": 111.875, "minY": 189.125, "maxX": 149.875, "maxY": 220.625}, "class_id": 37, "box_caption": "Ad 0.001", "scores": {"class_score": 0.0013856887817382812}, "domain": "pixel"}, {"position": {"minX": 111.5, "minY": 188.75, "maxX": 150.0, "maxY": 220.5}, "class_id": 18, "box_caption": "5h 0.001", "scores": {"class_score": 0.001384735107421875}, "domain": "pixel"}, {"position": {"minX": 111.75, "minY": 189.125, "maxX": 150.0, "maxY": 220.625}, "class_id": 47, "box_caption": "Ks 0.001", "scores": {"class_score": 0.00138092041015625}, "domain": "pixel"}, {"position": {"minX": 169.5, "minY": 17.90625, "maxX": 208.75, "maxY": 49.78125}, "class_id": 41, "box_caption": "Jd 0.001", "scores": {"class_score": 0.0013551712036132812}, "domain": "pixel"}, {"position": {"minX": 342.0, "minY": 195.25, "maxX": 373.0, "maxY": 227.25}, "class_id": 32, "box_caption": "9c 0.001", "scores": {"class_score": 0.001346588134765625}, "domain": "pixel"}, {"position": {"minX": 169.25, "minY": 18.09375, "maxX": 208.75, "maxY": 50.09375}, "class_id": 18, "box_caption": "5h 0.001", "scores": {"class_score": 0.0013275146484375}, "domain": "pixel"}, {"position": {"minX": 111.6875, "minY": 189.125, "maxX": 150.125, "maxY": 220.625}, "class_id": 41, "box_caption": "Jd 0.001", "scores": {"class_score": 0.001323699951171875}, "domain": "pixel"}, {"position": {"minX": 169.5, "minY": 17.984375, "maxX": 209.0, "maxY": 50.0}, "class_id": 2, "box_caption": "10h 0.001", "scores": {"class_score": 0.0013217926025390625}, "domain": "pixel"}, {"position": {"minX": 169.625, "minY": 18.078125, "maxX": 208.875, "maxY": 50.125}, "class_id": 25, "box_caption": "7d 0.001", "scores": {"class_score": 0.0013036727905273438}, "domain": "pixel"}, {"position": {"minX": 169.5, "minY": 17.90625, "maxX": 208.75, "maxY": 49.78125}, "class_id": 9, "box_caption": "3d 0.001", "scores": {"class_score": 0.0012874603271484375}, "domain": "pixel"}, {"position": {"minX": 111.875, "minY": 189.125, "maxX": 149.875, "maxY": 220.625}, "class_id": 9, "box_caption": "3d 0.001", "scores": {"class_score": 0.0012197494506835938}, "domain": "pixel"}, {"position": {"minX": 169.5, "minY": 17.78125, "maxX": 208.75, "maxY": 49.96875}, "class_id": 47, "box_caption": "Ks 0.001", "scores": {"class_score": 0.0012178421020507812}, "domain": "pixel"}, {"position": {"minX": 167.25, "minY": 180.875, "maxX": 200.0, "maxY": 212.625}, "class_id": 40, "box_caption": "Jc 0.001", "scores": {"class_score": 0.001216888427734375}, "domain": "pixel"}, {"position": {"minX": 169.5, "minY": 17.90625, "maxX": 208.75, "maxY": 49.78125}, "class_id": 43, "box_caption": "Js 0.001", "scores": {"class_score": 0.0012149810791015625}, "domain": "pixel"}, {"position": {"minX": 111.625, "minY": 189.0, "maxX": 149.875, "maxY": 220.5}, "class_id": 25, "box_caption": "7d 0.001", "scores": {"class_score": 0.0012121200561523438}, "domain": "pixel"}, {"position": {"minX": 167.25, "minY": 180.875, "maxX": 200.0, "maxY": 212.625}, "class_id": 31, "box_caption": "8s 0.001", "scores": {"class_score": 0.0012083053588867188}, "domain": "pixel"}, {"position": {"minX": 169.25, "minY": 18.09375, "maxX": 208.75, "maxY": 50.09375}, "class_id": 14, "box_caption": "4h 0.001", "scores": {"class_score": 0.0012083053588867188}, "domain": "pixel"}, {"position": {"minX": 111.75, "minY": 189.125, "maxX": 150.0, "maxY": 220.625}, "class_id": 22, "box_caption": "6h 0.001", "scores": {"class_score": 0.0012044906616210938}, "domain": "pixel"}, {"position": {"minX": 342.0, "minY": 195.25, "maxX": 373.0, "maxY": 227.25}, "class_id": 31, "box_caption": "8s 0.001", "scores": {"class_score": 0.00119781494140625}, "domain": "pixel"}, {"position": {"minX": 169.625, "minY": 18.078125, "maxX": 208.875, "maxY": 50.125}, "class_id": 29, "box_caption": "8d 0.001", "scores": {"class_score": 0.0011959075927734375}, "domain": "pixel"}, {"position": {"minX": 167.125, "minY": 181.0, "maxX": 199.875, "maxY": 212.5}, "class_id": 45, "box_caption": "Kd 0.001", "scores": {"class_score": 0.0011796951293945312}, "domain": "pixel"}, {"position": {"minX": 342.0, "minY": 195.25, "maxX": 373.0, "maxY": 227.25}, "class_id": 40, "box_caption": "Jc 0.001", "scores": {"class_score": 0.0011749267578125}, "domain": "pixel"}, {"position": {"minX": 111.75, "minY": 189.125, "maxX": 150.0, "maxY": 220.625}, "class_id": 29, "box_caption": "8d 0.001", "scores": {"class_score": 0.001140594482421875}, "domain": "pixel"}, {"position": {"minX": 341.5, "minY": 195.25, "maxX": 373.5, "maxY": 226.75}, "class_id": 45, "box_caption": "Kd 0.001", "scores": {"class_score": 0.0011339187622070312}, "domain": "pixel"}, {"position": {"minX": 111.125, "minY": 188.125, "maxX": 149.875, "maxY": 219.375}, "class_id": 42, "box_caption": "Jh 0.001", "scores": {"class_score": 0.0011281967163085938}, "domain": "pixel"}, {"position": {"minX": 169.5, "minY": 17.90625, "maxX": 208.75, "maxY": 49.78125}, "class_id": 22, "box_caption": "6h 0.001", "scores": {"class_score": 0.0011196136474609375}, "domain": "pixel"}, {"position": {"minX": 169.5, "minY": 17.78125, "maxX": 208.75, "maxY": 49.96875}, "class_id": 35, "box_caption": "9s 0.001", "scores": {"class_score": 0.0011043548583984375}, "domain": "pixel"}, {"position": {"minX": 111.75, "minY": 189.125, "maxX": 150.0, "maxY": 220.625}, "class_id": 35, "box_caption": "9s 0.001", "scores": {"class_score": 0.0010805130004882812}, "domain": "pixel"}, {"position": {"minX": 167.5, "minY": 180.5, "maxX": 200.5, "maxY": 213.0}, "class_id": 43, "box_caption": "Js 0.001", "scores": {"class_score": 0.001071929931640625}, "domain": "pixel"}, {"position": {"minX": 111.75, "minY": 189.125, "maxX": 150.0, "maxY": 220.625}, "class_id": 49, "box_caption": "Qd 0.001", "scores": {"class_score": 0.0010633468627929688}, "domain": "pixel"}, {"position": {"minX": 167.25, "minY": 180.875, "maxX": 200.0, "maxY": 212.625}, "class_id": 7, "box_caption": "2s 0.001", "scores": {"class_score": 0.001033782958984375}, "domain": "pixel"}, {"position": {"minX": 342.0, "minY": 195.25, "maxX": 373.0, "maxY": 227.25}, "class_id": 7, "box_caption": "2s 0.001", "scores": {"class_score": 0.0010290145874023438}, "domain": "pixel"}], "class_labels": {"0": "10c", "1": "10d", "2": "10h", "3": "10s", "4": "2c", "5": "2d", "6": "2h", "7": "2s", "8": "3c", "9": "3d", "10": "3h", "11": "3s", "12": "4c", "13": "4d", "14": "4h", "15": "4s", "16": "5c", "17": "5d", "18": "5h", "19": "5s", "20": "6c", "21": "6d", "22": "6h", "23": "6s", "24": "7c", "25": "7d", "26": "7h", "27": "7s", "28": "8c", "29": "8d", "30": "8h", "31": "8s", "32": "9c", "33": "9d", "34": "9h", "35": "9s", "36": "Ac", "37": "Ad", "38": "Ah", "39": "As", "40": "Jc", "41": "Jd", "42": "Jh", "43": "Js", "44": "Kc", "45": "Kd", "46": "Kh", "47": "Ks", "48": "Qc", "49": "Qd", "50": "Qh", "51": "Qs"}}